awssso/__init__.py
awssso/__main__.py
awssso/cli.py
awssso/config.py
awssso/helpers.py
awssso/saml.py
awssso/ssoclient.py
awssso/ssodriver.py
awssso-1.1.1.dist-info/LICENSE
awssso-1.1.1.dist-info/METADATA
awssso-1.1.1.dist-info/WHEEL
awssso-1.1.1.dist-info/entry_points.txt
awssso-1.1.1.dist-info/top_level.txt
awssso-1.1.1.dist-info/RECORD
