Metadata-Version: 2.1
Name: awssso
Version: 1.1.1
Summary: Command Line tool for AWS SSO Credentials
Home-page: http://github.com/wnkz/aws-sso
Author: wnkz
Author-email: wnkz@users.noreply.github.com
License: Apache License 2.0
Keywords: aws,sso,cloud,cli,credentials
Platform: UNKNOWN
Classifier: Development Status :: 5 - Production/Stable
Classifier: Environment :: Console
Classifier: Intended Audience :: Developers
Classifier: Intended Audience :: System Administrators
Classifier: Natural Language :: English
Classifier: License :: OSI Approved :: Apache Software License
Classifier: Operating System :: MacOS
Classifier: Operating System :: POSIX
Classifier: Programming Language :: Python :: 3.7
